geoalchemy2/__init__.py
geoalchemy2/_functions.py
geoalchemy2/_functions_helpers.py
geoalchemy2/alembic_helpers.py
geoalchemy2/comparator.py
geoalchemy2/elements.py
geoalchemy2/exc.py
geoalchemy2/functions.py
geoalchemy2/functions.pyi
geoalchemy2/py.typed
geoalchemy2/shape.py
geoalchemy2/utils.py
geoalchemy2/admin/__init__.py
geoalchemy2/admin/dialects/__init__.py
geoalchemy2/admin/dialects/common.py
geoalchemy2/admin/dialects/geopackage.py
geoalchemy2/admin/dialects/mysql.py
geoalchemy2/admin/dialects/postgresql.py
geoalchemy2/admin/dialects/sqlite.py
geoalchemy2/types/__init__.py
geoalchemy2/types/dialects/__init__.py
geoalchemy2/types/dialects/common.py
geoalchemy2/types/dialects/geopackage.py
geoalchemy2/types/dialects/mysql.py
geoalchemy2/types/dialects/postgresql.py
geoalchemy2/types/dialects/sqlite.py
GeoAlchemy2-0.15.2.dist-info/COPYING.rst
GeoAlchemy2-0.15.2.dist-info/METADATA
GeoAlchemy2-0.15.2.dist-info/WHEEL
GeoAlchemy2-0.15.2.dist-info/top_level.txt
GeoAlchemy2-0.15.2.dist-info/RECORD
