Metadata-Version: 2.1
Name: GeoAlchemy2
Version: 0.15.2
Summary: Using SQLAlchemy with Spatial Databases
Home-page: https://geoalchemy-2.readthedocs.io/en/stable/
Author: Eric Lemoine
Author-email: eric.lemoine@gmail.com
License: MIT
Project-URL: Tracker, https://github.com/geoalchemy/geoalchemy2/issues
Project-URL: Source, https://github.com/geoalchemy/geoalchemy2
Keywords: geo,gis,sqlalchemy,orm
Classifier: Development Status :: 4 - Beta
Classifier: Environment :: Plugins
Classifier: Operating System :: OS Independent
Classifier: Programming Language :: Python
Classifier: Programming Language :: Python :: 3.7
Classifier: Programming Language :: Python :: 3.8
Classifier: Programming Language :: Python :: 3.9
Classifier: Programming Language :: Python :: 3.10
Classifier: Programming Language :: Python :: 3.11
Classifier: Programming Language :: Python :: 3.12
Classifier: Intended Audience :: Information Technology
Classifier: License :: OSI Approved :: MIT License
Classifier: Topic :: Scientific/Engineering :: GIS
Requires-Python: >=3.7
License-File: COPYING.rst
Requires-Dist: SQLAlchemy>=1.4
Requires-Dist: packaging
Provides-Extra: shapely
Requires-Dist: Shapely>=1.7; extra == "shapely"
